sensortoolkit/__init__.py
sensortoolkit/calculate/__init__.py
sensortoolkit/calculate/_aqi.py
sensortoolkit/calculate/_concentration_trends.py
sensortoolkit/calculate/_convert_temp.py
sensortoolkit/calculate/_cv.py
sensortoolkit/calculate/_dewpoint.py
sensortoolkit/calculate/_intersensor_mean.py
sensortoolkit/calculate/_normalize.py
sensortoolkit/calculate/_nowcast_pm25.py
sensortoolkit/calculate/_ratio.py
sensortoolkit/calculate/_regression_stats.py
sensortoolkit/calculate/_rmse.py
sensortoolkit/calculate/_uptime.py
sensortoolkit/datetime_utils/__init__.py
sensortoolkit/datetime_utils/_format_date.py
sensortoolkit/datetime_utils/_get_timestamp_interval.py
sensortoolkit/datetime_utils/_set_datetime_index.py
sensortoolkit/datetime_utils/_time_averaging.py
sensortoolkit/datetime_utils/_timeframe_utils.py
sensortoolkit/deploy/__init__.py
sensortoolkit/deploy/_create_deploy_dict.py
sensortoolkit/deploy/_deployment_period.py
sensortoolkit/deploy/_get_max_conc.py
sensortoolkit/evaluation_objs/__init__.py
sensortoolkit/evaluation_objs/_performance_report.py
sensortoolkit/evaluation_objs/_sensor_eval.py
sensortoolkit/evaluation_objs/templates/placeholder_image.png
sensortoolkit/evaluation_objs/templates/CO/Reporting_Template_Base_CO.pptx
sensortoolkit/evaluation_objs/templates/NO2/Reporting_Template_Base_NO2.pptx
sensortoolkit/evaluation_objs/templates/O3/Reporting_Template_Base_O3.pptx
sensortoolkit/evaluation_objs/templates/PM10/Reporting_Template_Base_PM10.pptx
sensortoolkit/evaluation_objs/templates/PM25/Reporting_Template_Base_PM25.pptx
sensortoolkit/evaluation_objs/templates/SO2/Reporting_Template_Base_SO2.pptx
sensortoolkit/ingest/__init__.py
sensortoolkit/ingest/_processed_data_loader.py
sensortoolkit/ingest/_sensor_import.py
sensortoolkit/ingest/_standard_ingest.py
sensortoolkit/lib_utils/__init__.py
sensortoolkit/lib_utils/_check_type.py
sensortoolkit/lib_utils/_copy_datasets.py
sensortoolkit/lib_utils/_flatten_datasets.py
sensortoolkit/lib_utils/_flatten_list.py
sensortoolkit-1.1.0.dist-info/METADATA
sensortoolkit-1.1.0.dist-info/WHEEL
sensortoolkit-1.1.0.dist-info/top_level.txt
sensortoolkit-1.1.0.dist-info/RECORD
