Metadata-Version: 2.1
Name: sensortoolkit
Version: 1.1.0
Summary: Library for evaluating air sensor data
Author: Samuel Frederick, ORAU Contractor for U.S. EPA ORD
Maintainer: Andrea Clements
Maintainer-email: clements.andrea@epa.gov
License: The MIT License (MIT)
Project-URL: Source, https://github.com/USEPA/sensortoolkit
Project-URL: Documentation, https://sensortoolkit.readthedocs.io/en/latest/
Project-URL: Tracker, https://github.com/USEPA/sensortoolkit/issues
Project-URL: US EPA Air Sensor Toolbox, https://www.epa.gov/air-sensor-toolbox
Classifier: Programming Language :: Python :: 3.8
Classifier: Programming Language :: Python :: 3.9
Classifier: Development Status :: 4 - Beta
Classifier: Intended Audience :: Science/Research
Classifier: License :: OSI Approved :: MIT License
Classifier: Operating System :: MacOS
Classifier: Operating System :: Microsoft :: Windows
Classifier: Topic :: Scientific/Engineering
Classifier: Topic :: Scientific/Engineering :: Atmospheric Science
Requires-Python: >=3.8, <4
Requires-Dist: matplotlib
Requires-Dist: numpy
Requires-Dist: pandas<=1.3.5,>=1.3.0
Requires-Dist: pathlib2
Requires-Dist: python-pptx
Requires-Dist: requests
Requires-Dist: scipy
Requires-Dist: seaborn<=0.11.2
Requires-Dist: tabulate
Requires-Dist: statsmodels==0.13.5
Requires-Dist: urllib3
Requires-Dist: pip
Requires-Dist: chardet
Requires-Dist: timezonefinder
Requires-Dist: appdirs
Requires-Dist: charset-normalizer<=2.0.3
